atomic_operations/__init__.py
atomic_operations/consts.py
atomic_operations/exceptions.py
atomic_operations/parsers.py
atomic_operations/renderers.py
atomic_operations/views.py
drf_json_api_atomic_operations-0.4.0.dist-info/LICENSE
drf_json_api_atomic_operations-0.4.0.dist-info/METADATA
drf_json_api_atomic_operations-0.4.0.dist-info/WHEEL
drf_json_api_atomic_operations-0.4.0.dist-info/top_level.txt
drf_json_api_atomic_operations-0.4.0.dist-info/RECORD
