Metadata-Version: 2.1
Name: drf-json-api-atomic-operations
Version: 0.4.0
Summary: Extension for `django-rest-framework-json-api <https://github.com/django-json-api/django-rest-framework-json-api>`_ to support `atomic operations <https://jsonapi.org/ext/atomic/>`_.
Home-page: https://github.com/jokiefer/drf-json-api-atomic-operations/
Author: Jonas Kiefer
Author-email: jonas.kiefer@live.com
License: MIT-License
Platform: OS Independent
Classifier: Development Status :: 3 - Alpha
Classifier: Intended Audience :: Developers
Classifier: Natural Language :: English
Classifier: Topic :: Internet :: WWW/HTTP
Classifier: Environment :: Web Environment
Classifier: Framework :: Django
Classifier: Topic :: Software Development :: Libraries
Classifier: License :: OSI Approved :: MIT License
Classifier: Operating System :: OS Independent
Classifier: Framework :: Django
Classifier: Programming Language :: Python
Classifier: Programming Language :: Python :: 3.8
Classifier: Programming Language :: Python :: 3.9
Classifier: Programming Language :: Python :: 3.10
Requires-Python: >=3.8
License-File: LICENSE
Requires-Dist: djangorestframework-jsonapi>=6.0.0
Provides-Extra: tests
Requires-Dist: coverage; extra == "tests"
